uuid05/__init__.py
uuid05-0.0.4.data/scripts/uuid05
uuid05-0.0.4.dist-info/LICENSE
uuid05-0.0.4.dist-info/METADATA
uuid05-0.0.4.dist-info/WHEEL
uuid05-0.0.4.dist-info/top_level.txt
uuid05-0.0.4.dist-info/RECORD
