Metadata-Version: 2.1
Name: uuid05
Version: 0.0.4
Summary: Compact human-readable almost unique identifiers for temporary objects in small non-synchronizing distributed systems.
Home-page: https://github.com/strizhechenko/uuid05
Author: Oleg Strizhechenko
Author-email: oleg.strizhechenko@gmail.com
License: MIT
License-File: LICENSE
